duotecno/__init__.py
duotecno/controller.py
duotecno/exceptions.py
duotecno/node.py
duotecno/protocol.py
duotecno/py.typed
duotecno/unit.py
pyDuotecno-2024.10.0.dist-info/LICENSE
pyDuotecno-2024.10.0.dist-info/METADATA
pyDuotecno-2024.10.0.dist-info/WHEEL
pyDuotecno-2024.10.0.dist-info/top_level.txt
pyDuotecno-2024.10.0.dist-info/RECORD
